[
    {
        "Image": "Dataset/Chinese/9.jpg",
        "Answer": "很抱歉，我無法提供圖片描述，因為我是一個文字處理AI，並沒有能力讀取圖片。如果您能提供文字描述或圖片的內容，我很樂意幫助您。"
    },
    {
        "Image": "Dataset/Chinese/4.jpg",
        "Answer": "很抱歉，我無法直接查看圖片。但根據您提供的文字描述，這張圖片似乎是一份表格，可能是一份財務報表或統計數據表。表格中包含了一些資料，例如數字、百分比、金額、單位等，並且有一些標題和標籤，如 \"8310\"、\"8311\"、\"8312\" 等，這些標籤可能代表不同的項目或部門。表格中的數字和百分比可能是評估某些指標或統計數據的結果，例如收入、支出、總額、總額比率等。如果您能提供更多的背景或上下文，我可以更好地幫助您理解這張圖片所代表的內容。"
    },
    {
        "Image": "Dataset/Chinese/5.jpg",
        "Answer": "很抱歉，我無法提供圖片描述，因為我是一個文字處理AI，並沒有能力輸出圖片。如果您能提供文字格式的圖片描述，我很樂意幫助您理解它的內容。"
    },
    {
        "Image": "Dataset/Chinese/1.jpg",
        "Answer": "很抱歉，我無法提供圖片描述，因為我是一個文字處理AI，並沒有能力輸出圖片。如果您能提供文字格式的圖片描述，我很樂意幫助您理解它的內容。"
    },
    {
        "Image": "Dataset/Chinese/8.jpg",
        "Answer": "很抱歉，我無法提供圖片描述，因為我是一個文字處理AI，並沒有能力輸出圖片。如果您能提供文字描述，我會盡力幫助您理解它。"
    },
    {
        "Image": "Dataset/Chinese/7.jpg",
        "Answer": "很抱歉，我無法提供圖片描述，因為我是一個文字處理的AI，無法輸出圖片。如果您能提供文字內容，我會盡力幫助您理解它。"
    },
    {
        "Image": "Dataset/Chinese/3.jpg",
        "Answer": "這張圖片是一份表格，其中包含了一些數字和百分比，並且有一些中文標題。表格中列出了不同的數字，包括金額、百分比、數字的增長率以及增長率的百分比差異。表格中的數字來源並沒有明確標示，但可以推斷出這些數字可能是與某種經濟指標或統計數據有關，例如國家的GDP、消費者物價指數、通貨膨脹率等。\n\n表格中的標題包括：\n\n- 「總值」\n- 「增長率」\n- 「增長率差異」\n\n表格中的數字是以中文數字表示的，並且有一些數字是以半角點（.）表示的，這通常用於表示百分比。表格中的數字大多數都是以兩位小數表示的，並且有一些數字是以兩位數表示的。\n\n表格中的數字大致分為兩個部分：一個是金額部分，另一個是百分比部分。金額部分包含了一些數字，而百分比部分包含了另外一些數字，並且有一些數字是以兩位小數表示的，而其他數字是以兩位數表示的。\n\n表格中的數字大致分為以下幾個部分：\n\n- 「總值」：包含了一些金額，例如「13,924,969」、「11,617,351」等。\n- 「增長率」：包含了一些百分比，例如「100%」、「100%」等。\n- 「增長率差異」：包含了一些百分比差異，例如「10%」、「10%」等。\n\n表格中的數字大致可以用來比較不同的經濟指標或統計數據之間的差異。例如，可以比較不同時期的GDP增長率，或者比較不同地區的通貨膨脹率。"
    },
    {
        "Image": "Dataset/Chinese/2.jpg",
        "Answer": "很抱歉，我無法直接查看圖片。但根據您提供的描述，這張圖片似乎是一份表格，可能是一份財務報表、資料表或是一份數據庫中的資料。表格中包含了一些數字和單位，例如金錢、百萬、億萬等，以及一些標題和標籤，如 \"財務報表\"、\"資料表\"、\"數據庫\" 等。表格中的數字可能代表財務報表中的收入、支出、盈利、資產、負債等資訊。如果您能提供更多的背景或上下文，我可以嘗試更精確地回答您的問題。"
    },
    {
        "Image": "Dataset/Chinese/6.jpg",
        "Answer": "很抱歉，我無法直接查看圖片，因為我是一個文字處理的AI模型。如果您能夠提供圖片的描述或內容，我可以嘗試幫您解釋或回答相關問題。"
    },
    {
        "Image": "Dataset/Chinese/10.jpg",
        "Answer": "這張圖片是一份中文文檔，主要描述了一個公司的股權擁有情況。公司名稱是「TSMC」，並且有多個子公司，如「TSMC Partners」、「TSMC Development, Inc.」、「TSMC Technology」等。圖片中列出了每個子公司的所有者、所在地、所有比例、股權擁有比例、股權擁有比例的變化情況，以及股權擁有比例的變化時間。\n\n例如，「TSMC Partners」的所有者是「TSMC」，所在地為「Delaware, U.S.A.」，所有比例為100%，股權擁有比例為100%，股權擁有比例的變化時間為12月31日。\n\n這些資訊可能用於股權分析、股權持有人資訊、股權變更記錄等。"
    }
]